Workbook

Sheet Dashboard Summary
A1: SITE EXPENSE & PROJECT DASHBOARD
B3: Total Advance Received (மொத்த முன்பணம்) | C3: Total Expense Logged (மொத்த செலவு) | D3: Cash in Hand (Petty Cash) (கைவசம் உள்ள பணம்) | E3: Out of Pocket (Own Cash Used) (சொந்தமாக செய்த செலவு) | F3: Total Weekly Labor Paid (மொத்த வாராந்திர கூலி)
B4: =150000 -> 150000 | C4: =SUM('Expense Log'!E5:E100) -> 99400 | D4: =B4-SUMIF('Expense Log'!F5:F100, "Client Advance", 'Expense Log'!E5:E100) -> 105000 | E4: =SUMIF('Expense Log'!F5:F100, "Engineer Own Cash", 'Expense Log'!E5:E100) -> 4700 | F4: =SUM('Labor Weekly Salary'!G5:G100) -> 0
B7: Category | C7: Amount Spent (₹)
B8: Materials | C8: =SUM('Material Tracker'!H5:H100) -> 375000
B9: Labor Paid | C9: =SUM('Labor Weekly Salary'!G5:G100) -> 0
B10: Other General Site Exp | C10: =SUMIF('Expense Log'!C5:C100, "Others", 'Expense Log'!E5:E100) -> 4700
B11: Total Project Cost | C11: =SUM(C8:C10) -> 379700

Sheet Expense Log
A1: GENERAL EXPENSE LOG
A3: Date (தேதி) | B3: Bill No (பில் எண்) | C3: Category (வகை) | D3: Description (விவரம்) | E3: Amount Spent (செலவுத் தொகை) | F3: Payment Mode (பணம் செலுத்திய முறை) | G3: Remarks / Approval Status
A5: 2026-03-01 | B5: B-101 | C5: Materials | D5: Cement procurement partial | E5: 45000 | F5: Client Advance | G5: Approved by Senior
A6: 2026-03-02 | B6: B-102 | C6: Others | D6: Site safety signs & tape | E6: 1200 | F6: Engineer Own Cash | G6: Reimbursement Pending
A7: 2026-03-05 | B7: B-105 | C7: Others | D7: Emergency plumbing tool repair | E7: 3500 | F7: Engineer Own Cash | G7: Reimbursement Pending
D9: Total General Expenses: | E9: =SUM(E5:E8) -> 49700

Sheet Material Tracker
A1: MATERIAL INFLOW & TRACKER
A3: Date (தேதி) | B3: Material Name (பொருள் பெயர்) | C3: Vendor Name (வியாபாரி) | D3: Estimated Unit Price (₹) | E3: Actual Unit Price (₹) | F3: Quantity Received (அளவு) | G3: Unit (அலகு) | H3: Total Material Cost (₹) | I3: Price Deviation (விலை மாற்றம்)
A5: 2026-03-01 | B5: Cement | C5: ABC Traders | D5: 420 | E5: 450 | F5: 100 | G5: Bags | H5: =E5*F5 -> 45000 | I5: =E5-D5 -> 30
A6: 2026-03-03 | B6: Steel Rods | C6: XYZ Steel Corp | D6: 62000 | E6: 61500 | F6: 2 | G6: Tons | H6: =E6*F6 -> 123000 | I6: =E6-D6 -> -500
A7: 2026-03-04 | B7: River Sand | C7: Local Quarry | D7: 3500 | E7: 3900 | F7: 5 | G7: Units | H7: =E7*F7 -> 19500 | I7: =E7-D7 -> 400
G9: Total Material Cost: | H9: =SUM(H5:H8) -> 187500

Sheet Labor Attendance
A1: DAILY LABOR ATTENDANCE LOG
A3: Labor ID | B3: Labor Name | C3: Category | D3: Mon | E3: Tue | F3: Wed | G3: Thu | H3: Fri | I3: Sat | J3: Sun | K3: Total Days Present
A5: L01 | B5: Murugan | C5: Mason | D5: 1 | E5: 1 | F5: 1 | G5: 1 | H5: 1 | I5: 0.5 | J5: 0 | K5: =SUM(D5:J5) -> 5.5
A6: L02 | B6: Arumugam | C6: Mason | D6: 1 | E6: 1 | F6: 1 | G6: 1 | H6: 1 | I6: 1 | J6: 0 | K6: =SUM(D6:J6) -> 6
A7: L03 | B7: Kumar | C7: Helper | D7: 1 | E7: 1 | F7: 1 | G7: 0 | H7: 1 | I7: 1 | J7: 0 | K7: =SUM(D7:J7) -> 5
A8: L04 | B8: Ravi | C8: Helper | D8: 1 | E8: 0.5 | F8: 1 | G8: 1 | H8: 1 | I8: 1 | J8: 0 | K8: =SUM(D8:J8) -> 5.5

Sheet Labor Weekly Salary
A1: WEEKLY LABOR WAGES CALCULATION
A3: Labor ID | B3: Labor Name (பெயர்) | C3: Role Category | D3: Daily Wage Rate (₹) | E3: Total Days Present | F3: Gross Salary Owed (₹) | G3: Advance Paid (₹) | H3: Net Payable / Balance (₹)
A5: L01 | B5: Murugan | C5: Mason | D5: 900 | E5: ='Labor Attendance'!K5 -> 5.5 | F5: =D5*E5 -> 4950 | G5: 0 | H5: =F5-G5 -> 4950
A6: L02 | B6: Arumugam | C6: Mason | D6: 900 | E6: ='Labor Attendance'!K6 -> 6 | F6: =D6*E6 -> 5400 | G6: 0 | H6: =F6-G6 -> 5400
A7: L03 | B7: Kumar | C7: Helper | D7: 600 | E7: ='Labor Attendance'!K7 -> 5 | F7: =D7*E7 -> 3000 | G7: 0 | H7: =F7-G7 -> 3000
A8: L04 | B8: Ravi | C8: Helper | D8: 600 | E8: ='Labor Attendance'!K8 -> 5.5 | F8: =D8*E8 -> 3300 | G8: 0 | H8: =F8-G8 -> 3300
E9: Total Net Payout: | H9: =SUM(H5:H8) -> 16650
